util/__init__.py
util/validation.py
utils_autozone-0.0.11.dist-info/METADATA
utils_autozone-0.0.11.dist-info/WHEEL
utils_autozone-0.0.11.dist-info/licenses/LICENSE
utils_autozone-0.0.11.dist-info/RECORD
